README.md
setup.cfg
setup.py
yaml_acl/__init__.py
yaml_acl/base.py
yaml_acl/check.py
yaml_acl/parse.py
yaml_acl.egg-info/PKG-INFO
yaml_acl.egg-info/SOURCES.txt
yaml_acl.egg-info/dependency_links.txt
yaml_acl.egg-info/requires.txt
yaml_acl.egg-info/top_level.txt