Metadata-Version: 2.1
Name: yaml-acl
Version: 0.0.1
Summary: Simple YAML-based ACL parser and checker
Home-page: https://gitlab.com/nolash/euth
Author: Louis Holbrook
Author-email: dev@holbrook.no
License: GPL3
Keywords: ethereum
Platform: UNKNOWN
Classifier: Programming Language :: Python :: 3
Classifier: Operating System :: OS Independent
Classifier: Development Status :: 3 - Alpha
Classifier: Environment :: No Input/Output (Daemon)
Classifier: Intended Audience :: Developers
Classifier: License :: OSI Approved :: GNU General Public License v3 or later (GPLv3+)
Classifier: Topic :: Internet
Requires-Python: >=3.6
